[
  {
    "filename": "authentic_001.jpg",
    "path": "authentic/authentic_001.jpg",
    "label": "authentic",
    "tampering_type": null
  },
  {
    "filename": "authentic_002.jpg",
    "path": "authentic/authentic_002.jpg",
    "label": "authentic",
    "tampering_type": null
  },
  {
    "filename": "authentic_003.jpg",
    "path": "authentic/authentic_003.jpg",
    "label": "authentic",
    "tampering_type": null
  },
  {
    "filename": "authentic_004.jpg",
    "path": "authentic/authentic_004.jpg",
    "label": "authentic",
    "tampering_type": null
  },
  {
    "filename": "authentic_005.jpg",
    "path": "authentic/authentic_005.jpg",
    "label": "authentic",
    "tampering_type": null
  },
  {
    "filename": "authentic_006.jpg",
    "path": "authentic/authentic_006.jpg",
    "label": "authentic",
    "tampering_type": null
  },
  {
    "filename": "authentic_007.jpg",
    "path": "authentic/authentic_007.jpg",
    "label": "authentic",
    "tampering_type": null
  },
  {
    "filename": "authentic_008.jpg",
    "path": "authentic/authentic_008.jpg",
    "label": "authentic",
    "tampering_type": null
  },
  {
    "filename": "authentic_009.jpg",
    "path": "authentic/authentic_009.jpg",
    "label": "authentic",
    "tampering_type": null
  },
  {
    "filename": "authentic_010.jpg",
    "path": "authentic/authentic_010.jpg",
    "label": "authentic",
    "tampering_type": null
  },
  {
    "filename": "authentic_011.jpg",
    "path": "authentic/authentic_011.jpg",
    "label": "authentic",
    "tampering_type": null
  },
  {
    "filename": "authentic_012.jpg",
    "path": "authentic/authentic_012.jpg",
    "label": "authentic",
    "tampering_type": null
  },
  {
    "filename": "authentic_013.jpg",
    "path": "authentic/authentic_013.jpg",
    "label": "authentic",
    "tampering_type": null
  },
  {
    "filename": "authentic_014.jpg",
    "path": "authentic/authentic_014.jpg",
    "label": "authentic",
    "tampering_type": null
  },
  {
    "filename": "authentic_015.jpg",
    "path": "authentic/authentic_015.jpg",
    "label": "authentic",
    "tampering_type": null
  },
  {
    "filename": "authentic_016.jpg",
    "path": "authentic/authentic_016.jpg",
    "label": "authentic",
    "tampering_type": null
  },
  {
    "filename": "authentic_017.jpg",
    "path": "authentic/authentic_017.jpg",
    "label": "authentic",
    "tampering_type": null
  },
  {
    "filename": "authentic_018.jpg",
    "path": "authentic/authentic_018.jpg",
    "label": "authentic",
    "tampering_type": null
  },
  {
    "filename": "authentic_019.jpg",
    "path": "authentic/authentic_019.jpg",
    "label": "authentic",
    "tampering_type": null
  },
  {
    "filename": "authentic_020.jpg",
    "path": "authentic/authentic_020.jpg",
    "label": "authentic",
    "tampering_type": null
  },
  {
    "filename": "authentic_021.jpg",
    "path": "authentic/authentic_021.jpg",
    "label": "authentic",
    "tampering_type": null
  },
  {
    "filename": "authentic_022.jpg",
    "path": "authentic/authentic_022.jpg",
    "label": "authentic",
    "tampering_type": null
  },
  {
    "filename": "authentic_023.jpg",
    "path": "authentic/authentic_023.jpg",
    "label": "authentic",
    "tampering_type": null
  },
  {
    "filename": "authentic_024.jpg",
    "path": "authentic/authentic_024.jpg",
    "label": "authentic",
    "tampering_type": null
  },
  {
    "filename": "authentic_025.jpg",
    "path": "authentic/authentic_025.jpg",
    "label": "authentic",
    "tampering_type": null
  },
  {
    "filename": "authentic_026.jpg",
    "path": "authentic/authentic_026.jpg",
    "label": "authentic",
    "tampering_type": null
  },
  {
    "filename": "authentic_027.jpg",
    "path": "authentic/authentic_027.jpg",
    "label": "authentic",
    "tampering_type": null
  },
  {
    "filename": "authentic_028.jpg",
    "path": "authentic/authentic_028.jpg",
    "label": "authentic",
    "tampering_type": null
  },
  {
    "filename": "authentic_029.jpg",
    "path": "authentic/authentic_029.jpg",
    "label": "authentic",
    "tampering_type": null
  },
  {
    "filename": "authentic_030.jpg",
    "path": "authentic/authentic_030.jpg",
    "label": "authentic",
    "tampering_type": null
  },
  {
    "filename": "authentic_031.jpg",
    "path": "authentic/authentic_031.jpg",
    "label": "authentic",
    "tampering_type": null
  },
  {
    "filename": "authentic_032.jpg",
    "path": "authentic/authentic_032.jpg",
    "label": "authentic",
    "tampering_type": null
  },
  {
    "filename": "authentic_033.jpg",
    "path": "authentic/authentic_033.jpg",
    "label": "authentic",
    "tampering_type": null
  },
  {
    "filename": "authentic_034.jpg",
    "path": "authentic/authentic_034.jpg",
    "label": "authentic",
    "tampering_type": null
  },
  {
    "filename": "authentic_035.jpg",
    "path": "authentic/authentic_035.jpg",
    "label": "authentic",
    "tampering_type": null
  },
  {
    "filename": "authentic_036.jpg",
    "path": "authentic/authentic_036.jpg",
    "label": "authentic",
    "tampering_type": null
  },
  {
    "filename": "authentic_037.jpg",
    "path": "authentic/authentic_037.jpg",
    "label": "authentic",
    "tampering_type": null
  },
  {
    "filename": "authentic_038.jpg",
    "path": "authentic/authentic_038.jpg",
    "label": "authentic",
    "tampering_type": null
  },
  {
    "filename": "authentic_039.jpg",
    "path": "authentic/authentic_039.jpg",
    "label": "authentic",
    "tampering_type": null
  },
  {
    "filename": "authentic_040.jpg",
    "path": "authentic/authentic_040.jpg",
    "label": "authentic",
    "tampering_type": null
  },
  {
    "filename": "authentic_041.jpg",
    "path": "authentic/authentic_041.jpg",
    "label": "authentic",
    "tampering_type": null
  },
  {
    "filename": "authentic_042.jpg",
    "path": "authentic/authentic_042.jpg",
    "label": "authentic",
    "tampering_type": null
  },
  {
    "filename": "authentic_043.jpg",
    "path": "authentic/authentic_043.jpg",
    "label": "authentic",
    "tampering_type": null
  },
  {
    "filename": "authentic_044.jpg",
    "path": "authentic/authentic_044.jpg",
    "label": "authentic",
    "tampering_type": null
  },
  {
    "filename": "authentic_045.jpg",
    "path": "authentic/authentic_045.jpg",
    "label": "authentic",
    "tampering_type": null
  },
  {
    "filename": "authentic_046.jpg",
    "path": "authentic/authentic_046.jpg",
    "label": "authentic",
    "tampering_type": null
  },
  {
    "filename": "authentic_047.jpg",
    "path": "authentic/authentic_047.jpg",
    "label": "authentic",
    "tampering_type": null
  },
  {
    "filename": "authentic_048.jpg",
    "path": "authentic/authentic_048.jpg",
    "label": "authentic",
    "tampering_type": null
  },
  {
    "filename": "authentic_049.jpg",
    "path": "authentic/authentic_049.jpg",
    "label": "authentic",
    "tampering_type": null
  },
  {
    "filename": "authentic_050.jpg",
    "path": "authentic/authentic_050.jpg",
    "label": "authentic",
    "tampering_type": null
  },
  {
    "filename": "copy_move_001.jpg",
    "path": "tampered/copy_move/copy_move_001.jpg",
    "label": "tampered",
    "tampering_type": "copy_move"
  },
  {
    "filename": "copy_move_002.jpg",
    "path": "tampered/copy_move/copy_move_002.jpg",
    "label": "tampered",
    "tampering_type": "copy_move"
  },
  {
    "filename": "copy_move_003.jpg",
    "path": "tampered/copy_move/copy_move_003.jpg",
    "label": "tampered",
    "tampering_type": "copy_move"
  },
  {
    "filename": "copy_move_004.jpg",
    "path": "tampered/copy_move/copy_move_004.jpg",
    "label": "tampered",
    "tampering_type": "copy_move"
  },
  {
    "filename": "copy_move_005.jpg",
    "path": "tampered/copy_move/copy_move_005.jpg",
    "label": "tampered",
    "tampering_type": "copy_move"
  },
  {
    "filename": "copy_move_006.jpg",
    "path": "tampered/copy_move/copy_move_006.jpg",
    "label": "tampered",
    "tampering_type": "copy_move"
  },
  {
    "filename": "copy_move_007.jpg",
    "path": "tampered/copy_move/copy_move_007.jpg",
    "label": "tampered",
    "tampering_type": "copy_move"
  },
  {
    "filename": "copy_move_008.jpg",
    "path": "tampered/copy_move/copy_move_008.jpg",
    "label": "tampered",
    "tampering_type": "copy_move"
  },
  {
    "filename": "copy_move_009.jpg",
    "path": "tampered/copy_move/copy_move_009.jpg",
    "label": "tampered",
    "tampering_type": "copy_move"
  },
  {
    "filename": "copy_move_010.jpg",
    "path": "tampered/copy_move/copy_move_010.jpg",
    "label": "tampered",
    "tampering_type": "copy_move"
  },
  {
    "filename": "splicing_001.jpg",
    "path": "tampered/splicing/splicing_001.jpg",
    "label": "tampered",
    "tampering_type": "splicing"
  },
  {
    "filename": "splicing_002.jpg",
    "path": "tampered/splicing/splicing_002.jpg",
    "label": "tampered",
    "tampering_type": "splicing"
  },
  {
    "filename": "splicing_003.jpg",
    "path": "tampered/splicing/splicing_003.jpg",
    "label": "tampered",
    "tampering_type": "splicing"
  },
  {
    "filename": "splicing_004.jpg",
    "path": "tampered/splicing/splicing_004.jpg",
    "label": "tampered",
    "tampering_type": "splicing"
  },
  {
    "filename": "splicing_005.jpg",
    "path": "tampered/splicing/splicing_005.jpg",
    "label": "tampered",
    "tampering_type": "splicing"
  },
  {
    "filename": "splicing_006.jpg",
    "path": "tampered/splicing/splicing_006.jpg",
    "label": "tampered",
    "tampering_type": "splicing"
  },
  {
    "filename": "splicing_007.jpg",
    "path": "tampered/splicing/splicing_007.jpg",
    "label": "tampered",
    "tampering_type": "splicing"
  },
  {
    "filename": "splicing_008.jpg",
    "path": "tampered/splicing/splicing_008.jpg",
    "label": "tampered",
    "tampering_type": "splicing"
  },
  {
    "filename": "splicing_009.jpg",
    "path": "tampered/splicing/splicing_009.jpg",
    "label": "tampered",
    "tampering_type": "splicing"
  },
  {
    "filename": "splicing_010.jpg",
    "path": "tampered/splicing/splicing_010.jpg",
    "label": "tampered",
    "tampering_type": "splicing"
  },
  {
    "filename": "noise_injection_001.jpg",
    "path": "tampered/noise_injection/noise_injection_001.jpg",
    "label": "tampered",
    "tampering_type": "noise_injection"
  },
  {
    "filename": "noise_injection_002.jpg",
    "path": "tampered/noise_injection/noise_injection_002.jpg",
    "label": "tampered",
    "tampering_type": "noise_injection"
  },
  {
    "filename": "noise_injection_003.jpg",
    "path": "tampered/noise_injection/noise_injection_003.jpg",
    "label": "tampered",
    "tampering_type": "noise_injection"
  },
  {
    "filename": "noise_injection_004.jpg",
    "path": "tampered/noise_injection/noise_injection_004.jpg",
    "label": "tampered",
    "tampering_type": "noise_injection"
  },
  {
    "filename": "noise_injection_005.jpg",
    "path": "tampered/noise_injection/noise_injection_005.jpg",
    "label": "tampered",
    "tampering_type": "noise_injection"
  },
  {
    "filename": "noise_injection_006.jpg",
    "path": "tampered/noise_injection/noise_injection_006.jpg",
    "label": "tampered",
    "tampering_type": "noise_injection"
  },
  {
    "filename": "noise_injection_007.jpg",
    "path": "tampered/noise_injection/noise_injection_007.jpg",
    "label": "tampered",
    "tampering_type": "noise_injection"
  },
  {
    "filename": "noise_injection_008.jpg",
    "path": "tampered/noise_injection/noise_injection_008.jpg",
    "label": "tampered",
    "tampering_type": "noise_injection"
  },
  {
    "filename": "noise_injection_009.jpg",
    "path": "tampered/noise_injection/noise_injection_009.jpg",
    "label": "tampered",
    "tampering_type": "noise_injection"
  },
  {
    "filename": "noise_injection_010.jpg",
    "path": "tampered/noise_injection/noise_injection_010.jpg",
    "label": "tampered",
    "tampering_type": "noise_injection"
  },
  {
    "filename": "lighting_modification_001.jpg",
    "path": "tampered/lighting_modification/lighting_modification_001.jpg",
    "label": "tampered",
    "tampering_type": "lighting_modification"
  },
  {
    "filename": "lighting_modification_002.jpg",
    "path": "tampered/lighting_modification/lighting_modification_002.jpg",
    "label": "tampered",
    "tampering_type": "lighting_modification"
  },
  {
    "filename": "lighting_modification_003.jpg",
    "path": "tampered/lighting_modification/lighting_modification_003.jpg",
    "label": "tampered",
    "tampering_type": "lighting_modification"
  },
  {
    "filename": "lighting_modification_004.jpg",
    "path": "tampered/lighting_modification/lighting_modification_004.jpg",
    "label": "tampered",
    "tampering_type": "lighting_modification"
  },
  {
    "filename": "lighting_modification_005.jpg",
    "path": "tampered/lighting_modification/lighting_modification_005.jpg",
    "label": "tampered",
    "tampering_type": "lighting_modification"
  },
  {
    "filename": "lighting_modification_006.jpg",
    "path": "tampered/lighting_modification/lighting_modification_006.jpg",
    "label": "tampered",
    "tampering_type": "lighting_modification"
  },
  {
    "filename": "lighting_modification_007.jpg",
    "path": "tampered/lighting_modification/lighting_modification_007.jpg",
    "label": "tampered",
    "tampering_type": "lighting_modification"
  },
  {
    "filename": "lighting_modification_008.jpg",
    "path": "tampered/lighting_modification/lighting_modification_008.jpg",
    "label": "tampered",
    "tampering_type": "lighting_modification"
  },
  {
    "filename": "lighting_modification_009.jpg",
    "path": "tampered/lighting_modification/lighting_modification_009.jpg",
    "label": "tampered",
    "tampering_type": "lighting_modification"
  },
  {
    "filename": "lighting_modification_010.jpg",
    "path": "tampered/lighting_modification/lighting_modification_010.jpg",
    "label": "tampered",
    "tampering_type": "lighting_modification"
  },
  {
    "filename": "compression_artifacts_001.jpg",
    "path": "tampered/compression_artifacts/compression_artifacts_001.jpg",
    "label": "tampered",
    "tampering_type": "compression_artifacts"
  },
  {
    "filename": "compression_artifacts_002.jpg",
    "path": "tampered/compression_artifacts/compression_artifacts_002.jpg",
    "label": "tampered",
    "tampering_type": "compression_artifacts"
  },
  {
    "filename": "compression_artifacts_003.jpg",
    "path": "tampered/compression_artifacts/compression_artifacts_003.jpg",
    "label": "tampered",
    "tampering_type": "compression_artifacts"
  },
  {
    "filename": "compression_artifacts_004.jpg",
    "path": "tampered/compression_artifacts/compression_artifacts_004.jpg",
    "label": "tampered",
    "tampering_type": "compression_artifacts"
  },
  {
    "filename": "compression_artifacts_005.jpg",
    "path": "tampered/compression_artifacts/compression_artifacts_005.jpg",
    "label": "tampered",
    "tampering_type": "compression_artifacts"
  },
  {
    "filename": "compression_artifacts_006.jpg",
    "path": "tampered/compression_artifacts/compression_artifacts_006.jpg",
    "label": "tampered",
    "tampering_type": "compression_artifacts"
  },
  {
    "filename": "compression_artifacts_007.jpg",
    "path": "tampered/compression_artifacts/compression_artifacts_007.jpg",
    "label": "tampered",
    "tampering_type": "compression_artifacts"
  },
  {
    "filename": "compression_artifacts_008.jpg",
    "path": "tampered/compression_artifacts/compression_artifacts_008.jpg",
    "label": "tampered",
    "tampering_type": "compression_artifacts"
  },
  {
    "filename": "compression_artifacts_009.jpg",
    "path": "tampered/compression_artifacts/compression_artifacts_009.jpg",
    "label": "tampered",
    "tampering_type": "compression_artifacts"
  },
  {
    "filename": "compression_artifacts_010.jpg",
    "path": "tampered/compression_artifacts/compression_artifacts_010.jpg",
    "label": "tampered",
    "tampering_type": "compression_artifacts"
  }
]